[{"in_reply_to_user_id":"63137606","text":"@DougalDave270 @anOldbootie @PirateRoberts6 @michaelpbreton @TeesOnLine What a twat, I will never get the vaccine and couldn’t give. a FLYING F¥CK what c¥nts like you think \uD83D\uDE18","possibly_sensitive":false,"source":"Twitter for iPhone","lang":"en","created_at":"2022-03-16T21:46:20.000Z","author_id":"1491712239266578432","reply_settings":"everyone","conversation_id":"1504172383908868101","id":"1504212494465785860"},{"in_reply_to_user_id":"1003672320781807616","text":"@GovParsonMO Older folks, many lacking a car, for their vaccine last year travelled far. Parson #LetThemEatCake as their vax he’d forsake. Meanwhile, @eric_schmitt disgraced the Bar — as his candidacy voters bores, his own complicity he ignores.\nhttps://t.co/DPzYEbFqfS\nhttps://t.co/4p6JIUfTbI","possibly_sensitive":false,"attachments":{"media_keys":["7_1366447528552652800"]},"source":"Twitter for iPhone","lang":"en","created_at":"2022-03-16T21:46:17.000Z","author_id":"4095955278","reply_settings":"everyone","conversation_id":"1504194341236981760","id":"1504212482595819521"},{"in_reply_to_user_id":"1003672320781807616","text":"@GovParsonMO @rafredarrows @MOPartnership @MoEcoDevo Older folks, many lacking a car, for their vaccine last year travelled far. Parson #LetThemEatCake as their vax he’d forsake. Meanwhile, @eric_schmitt disgraced the Bar — as his candidacy voters bores, his own complicity he ignores.\nhttps://t.co/DPzYEbFqfS\nhttps://t.co/4p6JIUfTbI","possibly_sensitive":false,"attachments":{"media_keys":["7_1366447528552652800"]},"source":"Twitter for iPhone","lang":"en","created_at":"2022-03-16T21:46:12.000Z","author_id":"4095955278","reply_settings":"everyone","conversation_id":"1504206144515960832","id":"1504212462102474752"},{"text":"W.H.O. Delays Assessing Russia’s Sputnik Vaccine Over Ukraine War https://t.co/eDBsOPnCEY","possibly_sensitive":false,"source":"IFTTT","lang":"en","created_at":"2022-03-16T21:46:11.000Z","author_id":"1311208949044060161","reply_settings":"everyone","conversation_id":"1504212456691974151","id":"1504212456691974151"},{"in_reply_to_user_id":"1476268096390418441","text":"@VonKrimp Not ONE adverse effect in that report has been tied to vaccinations by anything more than proximate timing, which is meaningless.\n\nThe leading, serious adverse effect, was definitely, NOT, vaccine related. It was, literally, COVID.\nhttps://t.co/NlPc4Mp4VU","possibly_sensitive":false,"source":"Twitter for Android","lang":"en","created_at":"2022-03-16T21:46:09.000Z","author_id":"1433554491928834051","reply_settings":"everyone","conversation_id":"1504175429703413765","id":"1504212450014498816"},{"in_reply_to_user_id":"1003672320781807616","text":"@GovParsonMO @USAinUK @MoEcoDevo @MOPartnership Older folks, many lacking a car, for their vaccine last year travelled far. Parson #LetThemEatCake as their vax he’d forsake. Meanwhile, @eric_schmitt disgraced the Bar — as his candidacy voters bores, his own complicity he ignores.\nhttps://t.co/DPzYEbFqfS\nhttps://t.co/4p6JIUfTbI","possibly_sensitive":false,"attachments":{"media_keys":["7_1366447528552652800"]},"source":"Twitter for iPhone","lang":"en","created_at":"2022-03-16T21:46:07.000Z","author_id":"4095955278","reply_settings":"everyone","conversation_id":"1504206144515960832","id":"1504212439725793280"},{"text":"Two of China’s largest cities, Shenzhen and Shanghai, imposed stringent restrictions on Sunday on the movements of their residents, as a coronavirus outbreak continued to spread across much of mainland China reports the @NYTimes. #China #ports #COVID\nhttps://t.co/GPksfWD39o","possibly_sensitive":false,"source":"Sprout Social","lang":"en","created_at":"2022-03-16T21:46:00.000Z","author_id":"46256081","reply_settings":"everyone","conversation_id":"1504212413670903809","id":"1504212413670903809"},{"text":"Just happened to come across this. Written before COVID hit the U.S., and mostly about the Ebola vaccine, but illuminating nonetheless. https://t.co/AN7ooTSp9r","possibly_sensitive":false,"source":"Twitter Web App","lang":"en","created_at":"2022-03-16T21:45:55.000Z","author_id":"26496560","reply_settings":"everyone","conversation_id":"1504212392443580417","id":"1504212392443580417"},{"in_reply_to_user_id":"16302242","text":"@stephenasmith buddy I have no clue how @espn let’s you give health/vaccine advice on their platform.","possibly_sensitive":false,"source":"Twitter for iPhone","lang":"en","created_at":"2022-03-16T21:45:55.000Z","author_id":"31052299","reply_settings":"everyone","conversation_id":"1504212391772442629","id":"1504212391772442629"},{"in_reply_to_user_id":"54291839","text":"@gegeben @RetiredNHRN @kacrn91 the unvaccinated are not suffering from blood clots. There are plenty of studies to prove the vaccine causes blood clotting, you need to get over your Stockholm syndrome and face reality. If you took the gene therapy get a d-dimer test, find out the hard way.","possibly_sensitive":false,"source":"Twitter Web App","lang":"en","created_at":"2022-03-16T21:45:51.000Z","author_id":"1503520476068339714","reply_settings":"everyone","conversation_id":"1504117064839090181","id":"1504212374386999296"},{"in_reply_to_user_id":"1081443735869812736","text":"@venezianrey \nUnvaxxed NY athletes practice &amp; travel with their teams, but they can’t go into team locker rooms or play with their team.Unvaxxed visiting players are allowed to play in NY arenas &amp; stadiums. Please sign AND share this petition. \uD83C\uDFC0⚾️\uD83C\uDFC8\uD83C\uDFD0\uD83C\uDFD2\uD83C\uDFF8\nhttps://t.co/aLdK0oooVw","possibly_sensitive":true,"source":"Twitter for iPhone","lang":"en","created_at":"2022-03-16T21:45:51.000Z","author_id":"1048964565566984192","reply_settings":"everyone","conversation_id":"1504212374202597384","id":"1504212374202597384"},{"in_reply_to_user_id":"174473050","text":"@cspotweet And here is the daily by vaccine status\n\nhttps://t.co/ubvhaCQfyo https://t.co/V3P1ULUVwJ","possibly_sensitive":false,"attachments":{"media_keys":["3_1504212221965967364","3_1504212344678739974"]},"source":"Twitter Web App","lang":"en","created_at":"2022-03-16T21:45:46.000Z","author_id":"883489771548323840","reply_settings":"everyone","conversation_id":"1504211960509968397","id":"1504212353465782277"},{"text":"Lol u know it’s bad when snl is on board with us.  https://t.co/26EYD0suPe","possibly_sensitive":false,"source":"Twitter for iPhone","lang":"en","created_at":"2022-03-16T21:45:46.000Z","author_id":"1294803797882155009","reply_settings":"everyone","conversation_id":"1504212351322574848","id":"1504212351322574848"},{"text":"Ukraine just silently announced: First country to implement WEF's ‘Great Reset’ by setting up a Social Credit Application combining:\nUniversal Basic Income (UBI),\nDigital Identity &amp;\nVaccine Passport all within their Diia app\n@freedomfight369 @Darlene30564389 @TariqElnaga https://t.co/bRjpsE9xP5","possibly_sensitive":false,"source":"Twitter Web App","lang":"en","created_at":"2022-03-16T21:45:45.000Z","author_id":"1259130000969588737","reply_settings":"everyone","conversation_id":"1504212349862916097","id":"1504212349862916097"},{"in_reply_to_user_id":"331672974","text":"@theJeremyVine @Mara61785136 @YardleyShooting Why don’t you discuss it on your show then? Deaths and injuries from covid vaccines. get people on your show who have been permanently disabled from the vaccine and people whose loved ones died from covid vaccines. You haven’t got the balls. Spineless the lot of you","possibly_sensitive":false,"source":"Twitter for iPad","lang":"en","created_at":"2022-03-16T21:45:40.000Z","author_id":"1027928276088631296","reply_settings":"everyone","conversation_id":"1504096561164341252","id":"1504212328342073355"},{"in_reply_to_user_id":"2323580552","text":"@danielgoyal @GlenGirl2 @StryderBourke In practical terms, I guess this guy wouldn't have been offered the treatment. And if this is the situation in England, I dread to think what it's like in less wealthy nations. \n\nThose drugs need to be as available as paracetamol.\n\nhttps://t.co/fLrvPfleTo","possibly_sensitive":false,"source":"Twitter Web App","lang":"en","created_at":"2022-03-16T21:45:39.000Z","author_id":"2323580552","reply_settings":"everyone","conversation_id":"1503887475961434122","id":"1504212323304677380"},{"in_reply_to_user_id":"830824804596871169","text":"@VancityJohnny Not ONE adverse effect in that report has been tied to vaccinations by anything more than proximate timing, which is meaningless.\n\nThe leading, serious adverse effect, was definitely, NOT, vaccine related. It was, literally, COVID.\nhttps://t.co/NlPc4Mp4VU","possibly_sensitive":false,"source":"Twitter for Android","lang":"en","created_at":"2022-03-16T21:45:30.000Z","author_id":"1433554491928834051","reply_settings":"everyone","conversation_id":"1504181265397796865","id":"1504212287694913542"},{"text":"Looking at Digital ID for Alberta and Ontario. As part of its use, the ‘Health Records’ section contains vaccine history.\n\nVaccine Passports just moving over to Digital ID.\n\nAlberta\nhttps://t.co/NG0de85Lib https://t.co/qhvBpeALvI","possibly_sensitive":false,"attachments":{"media_keys":["3_1504212232384753667","3_1504212232388886530","3_1504212232380588032","3_1504212232539889666"]},"source":"Twitter for iPhone","lang":"en","created_at":"2022-03-16T21:45:18.000Z","author_id":"1319792941825667072","reply_settings":"everyone","conversation_id":"1504212236478427141","id":"1504212236478427141"},{"text":"Mar 16 #COVID19AB case numbers:\nIncrease of 593 cases in the past 24 hrs\n4 new deaths reported in the past 24 hrs, 4,013 to date\n989 in hospital, 70 in ICU\n6,449 active cases\n3,166 tests on Mar 15\n8,544,273 vaccine doses as of Mar 15\nMore info: https://t.co/Y7SDViaxct https://t.co/R0bT6ZSX2M","possibly_sensitive":false,"attachments":{"media_keys":["3_1504212194392649731"]},"source":"Emplifi","lang":"en","created_at":"2022-03-16T21:45:09.000Z","author_id":"34747812","reply_settings":"everyone","conversation_id":"1504212198209384448","id":"1504212198209384448"},{"in_reply_to_user_id":"1462889411729756163","text":"idc if you think it’s okay for her to not get the vaccine, but her spreading fake news and spreading harmful news is so beyond fucked up. everyone has a right to their opinion rightfully so, but at a point when is she gonna stop spreading fake news","possibly_sensitive":false,"source":"Twitter for iPhone","lang":"en","created_at":"2022-03-16T21:45:09.000Z","author_id":"1462889411729756163","reply_settings":"everyone","conversation_id":"1504211785267613697","id":"1504212197932642304"},{"text":"Damn vaccine is a joke https://t.co/6TAZEqHe1u","possibly_sensitive":false,"attachments":{"media_keys":["3_1504212192178184197"]},"source":"Twitter for iPhone","lang":"en","created_at":"2022-03-16T21:45:08.000Z","author_id":"1476718976017346564","reply_settings":"everyone","conversation_id":"1504212194363387912","id":"1504212194363387912"},{"text":"Dr Ashley Bloomfield is now hinting that vaccine passes, mandates, and gathering limits are likely to be scrapped by April 12. https://t.co/wWC0h2ySE7","possibly_sensitive":false,"attachments":{"media_keys":["7_1504212125316644865"]},"source":"Twitter for iPhone","lang":"en","created_at":"2022-03-16T21:45:06.000Z","author_id":"1463032969484926980","reply_settings":"everyone","conversation_id":"1504212186809335809","id":"1504212186809335809"},{"in_reply_to_user_id":"1490733344828628994","text":"@Tsnyder_74 @pjstarlord @AesPolitics The first probably also hyperbolic. The second is also true. From the CDC - https://t.co/Af4HobD4Nr. The 3rd, also true: https://t.co/olOCmFL6wk","possibly_sensitive":false,"source":"Twitter for iPhone","lang":"en","created_at":"2022-03-16T21:45:05.000Z","author_id":"16829218","reply_settings":"everyone","conversation_id":"1503530827522752518","id":"1504212179372847104"},{"in_reply_to_user_id":"946018506268700672","text":"@blackintheempir @MrDelightful2 Oh, my.\n1 hour ago.\n\nUkraine just silently announced it’s the first country to implement the WEF's ‘Great Reset’ by setting up a Social Credit Application combining Universal Basic Income (UBI), a Digital Identity &amp; a Vaccine Passport all within their Diia app.","possibly_sensitive":false,"source":"Twitter for Android","lang":"en","created_at":"2022-03-16T21:45:01.000Z","author_id":"1128862538639265792","reply_settings":"everyone","conversation_id":"1504096709131001861","id":"1504212162323042313"},{"in_reply_to_user_id":"1428561715478765572","text":"@millenamos @joshg99 @IsraelMOH @NitzanHorowitz @RobertKennedyJr @FatEmperor @PECC_Israel Ah sorry -- I was responding in general to the question of how we know that there cannot be a huge spike of vaccine-caused deaths in spite of the fact that VAERs has a huge spike in reported deaths in the few days after vaccination.\n\nYou are asking about the specific CDC study...","possibly_sensitive":false,"source":"Twitter Web App","lang":"en","created_at":"2022-03-16T21:45:00.000Z","author_id":"2927122207","reply_settings":"everyone","conversation_id":"1495048760807862275","id":"1504212159252860937"},{"in_reply_to_user_id":"2756928227","text":"@RagToo @ATInsider @whykeepitup @BreezerGalway @SpyVsSpy20 @factode305 @g_ballew @SwordtheChemist @WeRone777 @philippapotts @radke_4 @stephan19573 @nevercunninplan @marcush87747500 @judysimpson222 @Iron_Mechanic @Nemeses667 @PrezJoeyB @AntonyGoodman5 @SirGorden @Sharky_vs_Evil @WaitingForPerot @bitcheswitches5 @Angelaisawake @Angelanashville @SwaledaleMutton @Lizzy_Lang7 @1Geofferson82 @badboyntx @tigresseleanor @JujuliaGrace @Natasha_KC1 @KrochetxKorner @jimbonail @Captain_EyebaII Vaccine-induced thrombotic thrombocytopenia caused by Covid Clot Shots are quite frequent as shown in the Pfizer data dump ordered by the Courts. \nYou know? The data that the FDA + Pfizer tried to hide till the year 2097. That data Einstein \uD83D\uDE05\nYou people are blind \uD83D\uDC11 \uD83D\uDC0F \uD83D\uDC11 \uD83D\uDC0F","possibly_sensitive":false,"source":"Twitter for Android","lang":"en","created_at":"2022-03-16T21:44:56.000Z","author_id":"992923553010999298","reply_settings":"everyone","conversation_id":"1404236426309423105","id":"1504212144686084100"},{"text":"Mayor Adams signals willingness to scrap COVID vaccine rule for NYC sports players: ‘We are going to work this out’ https://t.co/NhowFFQYbJ","possibly_sensitive":false,"source":"WordPress.com","lang":"en","created_at":"2022-03-16T21:44:51.000Z","author_id":"1476165846057644034","reply_settings":"everyone","conversation_id":"1504212121722236928","id":"1504212121722236928"},{"in_reply_to_user_id":"1197670629186719744","text":"@vegasknows2 @theHooHaagroove @jtomase I don’t know where you’re getting your medical information from but vaccines have never in medical history ever stopped you from getting the thing you’re being vaccinated with. It’s always been to prevent further harm. Your chances of dying from Covid go way up without a vaccine.","possibly_sensitive":false,"source":"Twitter for iPhone","lang":"en","created_at":"2022-03-16T21:44:44.000Z","author_id":"209735229","reply_settings":"everyone","conversation_id":"1504159951568125955","id":"1504212092760457216"},{"text":"The CDC is suggesting more time between the first and second doses of the COVID vaccine for some people. Here’s why https://t.co/QqWvdIXu9X","possibly_sensitive":false,"source":"WordPress.com","lang":"en","created_at":"2022-03-16T21:44:43.000Z","author_id":"982124664657928192","reply_settings":"everyone","conversation_id":"1504212086766903296","id":"1504212086766903296"},{"in_reply_to_user_id":"297564259","text":"@dale_susan @PlanetEarth_HD Actually, unvaccinated people report more very mild symptoms. Have you ever thought in the opposite direction: the vaccine causes more severe infections with each additional shot?","possibly_sensitive":false,"source":"Twitter Web App","lang":"en","created_at":"2022-03-16T21:44:40.000Z","author_id":"966045720","reply_settings":"everyone","conversation_id":"1503858920233869313","id":"1504212076276953091"},{"in_reply_to_user_id":"1256900626740588545","text":"@AngryKaren1 @ullho @mardic123 @CDN4WorldPeace Behave ! all you do is listen to msm propaganda \nThey know they don't have any long term data.\nThey know the vaccines can cause horrendous side effects.\nThey know there are alternatives to vaccines.\nThey know the vaccine has caused deaths.","possibly_sensitive":false,"source":"Twitter for Android","lang":"en","created_at":"2022-03-16T21:44:39.000Z","author_id":"1264406293466550272","reply_settings":"everyone","conversation_id":"1503740070762852356","id":"1504212073781379088"},{"text":"Convenient! \nUkraine quietly announced it’s the first country to implement the WEF's ‘Great Reset’ by setting up a Social Credit Application combining Universal Basic Income (UBI), a Digital Identity &amp; a Vaccine Passport all within their Diia app. https://t.co/XYj2F5JFoy","possibly_sensitive":false,"source":"Twitter Web App","lang":"en","created_at":"2022-03-16T21:44:39.000Z","author_id":"21478597","reply_settings":"everyone","conversation_id":"1504212071478616067","id":"1504212071478616067"},{"in_reply_to_user_id":"485349250","text":"@HetuJo @AnnechristineV3 @tvanouvelles Source : drees\uD83C\uDDEB\uD83C\uDDF7 (Direction de la Recherche, des Études, de l'Évaluation et des Statistiques) et  @LCI \uD83E\uDD37‍♂️ je suis double vacciné au cas ou tu me traiterai de « non vaxx » https://t.co/vgpZRF7wRs","possibly_sensitive":false,"attachments":{"media_keys":["3_1504212067045285895"]},"source":"Twitter for iPhone","lang":"fr","created_at":"2022-03-16T21:44:39.000Z","author_id":"1448548463050952707","reply_settings":"everyone","conversation_id":"1504176932149248003","id":"1504212070270746628"},{"in_reply_to_user_id":"1149242040414298113","text":"@NakedCowboys18 @BuckeyeFin @BRebellion777 @TheoFleury14 Also, the vaccine manufacturers have developed the mRNA \"vaccines\" quicker than ever before in modern history. The fastest ever before was Ebola which took 4 years and was seriously rushed. So, this was not \"any medicine\". https://t.co/jPiJhp744b","possibly_sensitive":false,"attachments":{"media_keys":["3_1504211979212361729"]},"source":"Twitter Web App","lang":"en","created_at":"2022-03-16T21:44:35.000Z","author_id":"1149242040414298113","reply_settings":"everyone","conversation_id":"1503837855411539974","id":"1504212057096343555"},{"in_reply_to_user_id":"500273723","text":"@TyTheFisch Putin is on the right side of all of this. Do some research. He did not mandate the vaccine in his country. He gave freedom of choice!","possibly_sensitive":false,"source":"Twitter for Android","lang":"en","created_at":"2022-03-16T21:44:27.000Z","author_id":"1447469394490130435","reply_settings":"everyone","conversation_id":"1504135384296480777","id":"1504212022711357443"},{"in_reply_to_user_id":"1476321330303754247","text":"@SeekTruthCare @ChazzieCheese @Delta @TSA 3x what? I had covid then later the vaccine and the vaccine side-effects were worse except for the lack of taste for a week. I should have just skipped the cancer causing vaccine.","possibly_sensitive":false,"source":"Plume for Android","lang":"en","created_at":"2022-03-16T21:44:23.000Z","author_id":"611106546","reply_settings":"everyone","conversation_id":"1503719118687678472","id":"1504212005602816002"},{"in_reply_to_user_id":"96906231","text":"@thevivafrei OK so isn't a vaccine supposed to protect a person? So wouldn't even 1 serious side effect be wrong? \nDidn't they pull a polio vaccine after like 43 deaths? (number could be wrong) \nHow many young healthy peoples lives has this destroyed and no one gives a fuck, which is sad","possibly_sensitive":false,"source":"Twitter for Android","lang":"en","created_at":"2022-03-16T21:44:23.000Z","author_id":"1487968030965575680","reply_settings":"everyone","conversation_id":"1504138637281267714","id":"1504212004172611597"},{"text":"As long as you block the streets and claim you're protesting vaccine mandates, you can ignore stuff like this.\n\nRight, Ottawa? https://t.co/vaPNtz0B0W","possibly_sensitive":false,"source":"Twitter Web App","lang":"en","created_at":"2022-03-16T21:44:22.000Z","author_id":"479091810","reply_settings":"everyone","conversation_id":"1504212001949638661","id":"1504212001949638661"},{"in_reply_to_user_id":"38340482","text":"@cultqueengirlie and it’s like 1) how do I explain to you a matter of global public health is very different than ONE individual’s personal decision? 2) these anti-abortion laws want to put people IN JAIL. Refusing the vaccine means you might lose your job but U WONT GET ARRESTED","possibly_sensitive":false,"source":"Twitter for iPhone","lang":"en","created_at":"2022-03-16T21:44:22.000Z","author_id":"252360015","reply_settings":"everyone","conversation_id":"1504136492330930178","id":"1504212000431296531"},{"in_reply_to_user_id":"828948086361903105","text":"@JeannetteChine1 @RealDeniseWelch The N95 masks do work. I had a maskless hairdresser last year who was working whilst covid positive, and I wore one and didn’t get it. She was in my face for 3 hours with no ventilation. I don’t want the vaccine but happily wear a mask.","possibly_sensitive":false,"source":"Twitter for iPhone","lang":"en","created_at":"2022-03-16T21:44:19.000Z","author_id":"3352303769","reply_settings":"everyone","conversation_id":"1503885391467728896","id":"1504211989492604931"},{"text":"You write this after 55 000 vaccine side effects hv been released by Pfizer?\nThe vaccines have seen their day. Trials take at least 6years. 4months for Pfizer. That\uD83C\uDDFA\uD83C\uDDF8judge would not accept the 75 yr. timeline for reveal\uD83D\uDC4F\uD83D\uDC4F\nSo plz. Just stop. \nSigned:A #sideeffects Canadian\uD83C\uDDE8\uD83C\uDDE6. https://t.co/TqEHHIe6mI","possibly_sensitive":false,"source":"Twitter for iPad","lang":"en","created_at":"2022-03-16T21:44:17.000Z","author_id":"1343666627209015296","reply_settings":"everyone","conversation_id":"1504211979484991497","id":"1504211979484991497"},{"in_reply_to_user_id":"1477579358567112704","text":"@WuhanVariant @BBCNews @bbc5live Nothing in life is without risk. It’s incredibly sad that this happened. But the risk of a reaction like this is minuscule and likely you’d have just as bad a reaction to the disease a vaccine protects from as well. These vaccines have saved millions of lives. Sadly not this life","possibly_sensitive":false,"source":"Twitter for iPhone","lang":"en","created_at":"2022-03-16T21:44:11.000Z","author_id":"9300842","reply_settings":"everyone","conversation_id":"1504208224400162822","id":"1504211953954304003"},{"in_reply_to_user_id":"1434525047696265218","text":"@truthseeker5580 @JonnyPilch09 @sophielouisecc If only vaccine will stop the spread...","possibly_sensitive":false,"source":"Twitter for Android","lang":"en","created_at":"2022-03-16T21:44:11.000Z","author_id":"337909870","reply_settings":"everyone","conversation_id":"1504174537289646087","id":"1504211952746352644"},{"text":"Mumps Infection With Symptoms of Parotitis, Pancreatitis, &amp; Orchitis Concurrently in an Adolescent Male “waning of vaccine-induced immunity &amp; low efficacy of mumps component of measles, mumps, and rubella (MMR) vaccine could be the reasons for the same.” https://t.co/EsvE6S82ZB","possibly_sensitive":false,"source":"Twitter for iPhone","lang":"en","created_at":"2022-03-16T21:44:10.000Z","author_id":"801569962921955328","reply_settings":"everyone","conversation_id":"1504211949957046276","id":"1504211949957046276"},{"in_reply_to_user_id":"1258216632163250177","text":"@LynnOwe53622654 @pfizer CHD Says Pfizer and FDA Dropped Data Bombshell on COVID Vaccine Consumers -\"These findings should put an immediate end to the Pfizer COVID vaccines. \" https://t.co/zI23FtRTHv","possibly_sensitive":false,"source":"Twitter for Android","lang":"en","created_at":"2022-03-16T21:44:08.000Z","author_id":"1261036521752158209","reply_settings":"everyone","conversation_id":"1504203396496039939","id":"1504211942910554113"},{"in_reply_to_user_id":"831368907730608128","text":"@stevero40104467 brother from another mother! Always happy to promote all the Denver restaurants that had a vaccine requirement. They all should be put out of biz. https://t.co/eocLygo76L","possibly_sensitive":false,"attachments":{"media_keys":["3_1504211934828146688","3_1504211938204524545"]},"source":"Echofon","lang":"en","created_at":"2022-03-16T21:44:08.000Z","author_id":"119950542","reply_settings":"everyone","conversation_id":"1504211940251365378","id":"1504211940251365378"},{"in_reply_to_user_id":"285924742","text":"@TonyDz77 @itsmylifetlktlk @tedcruz @All100Senators Vaccine mandates is what they were protesting, you were lied to","possibly_sensitive":false,"source":"Twitter for iPhone","lang":"en","created_at":"2022-03-16T21:44:07.000Z","author_id":"974838956595580929","reply_settings":"everyone","conversation_id":"1503922139803664384","id":"1504211939651686402"},{"in_reply_to_user_id":"868301244099698688","text":"@IlovemyFreegum @NHKathySullivan @NHHouseGOP It astounds me the same people who want movement licenses based on vaccine status oppose voter authentication, calling it \"vote suppression\".\n\nBut not \"movement suppression\". https://t.co/U0pA70ZiQA","possibly_sensitive":false,"source":"Twitter Web App","lang":"en","created_at":"2022-03-16T21:44:05.000Z","author_id":"3013408319","reply_settings":"everyone","conversation_id":"1504152442459590662","id":"1504211929199427584"},{"text":"Now would be a good idea to allow and increase vaccine coverage in under-12 age groups and implement high quality ventilation and a mass rollout of air filters at the very least.\n\nGovernment plan of removing free testing and measures will break before it is even implemented..","possibly_sensitive":false,"source":"Twitter for Android","lang":"en","created_at":"2022-03-16T21:43:58.000Z","author_id":"1726635955","reply_settings":"everyone","conversation_id":"1504211900317511680","id":"1504211900317511680"},{"text":"https://t.co/8gvOP2oPWF","possibly_sensitive":false,"source":"Twitter for Android","lang":"und","created_at":"2022-03-16T21:43:56.000Z","author_id":"1494048442942955522","reply_settings":"everyone","conversation_id":"1504211893107503114","id":"1504211893107503114"},{"in_reply_to_user_id":"3018960919","text":"@RebelNewsOnline So does that mean you are finally going to drop all discriminatory vaccine mandates @JustinTrudeau? Do you actually mean what you just said about the right to autonomy?","possibly_sensitive":false,"source":"Twitter for iPhone","lang":"en","created_at":"2022-03-16T21:43:55.000Z","author_id":"2590608853","reply_settings":"everyone","conversation_id":"1504130056167247883","id":"1504211889215004672"},{"in_reply_to_user_id":"1501341376796979202","text":"@BlowerRural @DonnaI16876888 @CDCgov https://t.co/CC2eZ6c7F7","possibly_sensitive":false,"source":"Twitter for iPhone","lang":"und","created_at":"2022-03-16T21:43:55.000Z","author_id":"1347917501150224389","reply_settings":"everyone","conversation_id":"1503834671372595200","id":"1504211888430895104"},{"in_reply_to_user_id":"41702018","text":"@EssexPR https://t.co/1gA0Smqu4n","possibly_sensitive":false,"source":"Twitter for Android","lang":"und","created_at":"2022-03-16T21:43:53.000Z","author_id":"20223562","reply_settings":"everyone","conversation_id":"1504024702712438786","id":"1504211879819943939"},{"in_reply_to_user_id":"1481749080766361600","text":"@BenJTavsfan And how does this possibly make sense if that’s true?\n\nhttps://t.co/OZEqzVivY9\n\nhttps://t.co/JCgF4YjjR2","possibly_sensitive":false,"source":"Twitter for iPhone","lang":"en","created_at":"2022-03-16T21:43:51.000Z","author_id":"16631823","reply_settings":"everyone","conversation_id":"1504203008275529731","id":"1504211871074762757"},{"in_reply_to_user_id":"257343658","text":"@JosieStem @DarkNight3141 @SteveDeaceShow That depends on your age and health. And just like you said we won’t know for many years what the effect is on children during Covid it’s the same for the vaccine. It was not researched for years. There are zero long term studies on it.","possibly_sensitive":false,"source":"Twitter for iPhone","lang":"en","created_at":"2022-03-16T21:43:49.000Z","author_id":"1267671890073489408","reply_settings":"everyone","conversation_id":"1504090077236019201","id":"1504211862140858369"},{"text":"As virus data grows, the J.&amp;J. vaccine holds its own. https://t.co/HwsTyKdmRn","possibly_sensitive":false,"source":"IFTTT","lang":"en","created_at":"2022-03-16T21:43:46.000Z","author_id":"1302092399863242752","reply_settings":"everyone","conversation_id":"1504211851592323073","id":"1504211851592323073"},{"in_reply_to_user_id":"610231648","text":"@Remifasol57 Id1ot . . \nhttps://t.co/TD9bsjQXtR","possibly_sensitive":false,"source":"Twitter for Android","lang":"en","created_at":"2022-03-16T21:43:45.000Z","author_id":"1468955148869201929","reply_settings":"everyone","conversation_id":"1504128018398289924","id":"1504211843652493314"},{"in_reply_to_user_id":"1259410284575416321","text":"@RealCarlVernon I developed tinnitus after my first vaccine.","possibly_sensitive":false,"source":"Twitter for iPhone","lang":"en","created_at":"2022-03-16T21:43:42.000Z","author_id":"877114380","reply_settings":"everyone","conversation_id":"1504050350529122308","id":"1504211832373923840"},{"text":"2022 March 16 - Dropping vaccine testing at international borders is an overdue and welcome announcement. Canada will still have to be concerned about people coming in from China, where Covid is once again on the rise. https://t.co/fpK7lOoMA1","possibly_sensitive":false,"source":"Twitter Web App","lang":"en","created_at":"2022-03-16T21:43:41.000Z","author_id":"796519688268369920","reply_settings":"everyone","conversation_id":"1504211830083784704","id":"1504211830083784704"},{"in_reply_to_user_id":"41702018","text":"@EssexPR @WhosFibbing The benefits of the vaccine are negligible at best.\nWe know that, why can't medical just admit that and deal with issues and dangers head on?","possibly_sensitive":false,"source":"Twitter for Android","lang":"en","created_at":"2022-03-16T21:43:41.000Z","author_id":"819734722032988160","reply_settings":"everyone","conversation_id":"1504024702712438786","id":"1504211827474894850"},{"text":"Living with COVID-19: Answering vaccine questions &amp; myths\n\nFact #1:\nIt may seem like more vaccinated people catch COVID-19 than unvaccinated, but there are considerably more fully vaccinated people in Saskatchewan – approximately 908,000 fully vaccinated to 185,000 unvaccinated. https://t.co/nI9WaSNYPg","possibly_sensitive":false,"attachments":{"media_keys":["3_1504211720717410312"]},"source":"Twitter Web App","lang":"en","created_at":"2022-03-16T21:43:40.000Z","author_id":"134198093","reply_settings":"mentionedUsers","conversation_id":"1504211822471258114","id":"1504211822471258114"},{"text":"Ukraine just silently announced: First country to implement WEF's ‘Great Reset’ by setting up a Social Credit Application combining:\nUniversal Basic Income (UBI),\nDigital Identity &amp;\nVaccine Passport all within their Diia app\n@LivePDDave1 @JamesMelville @LegendaryEnergy https://t.co/5O0Dify0ji","possibly_sensitive":false,"source":"Twitter Web App","lang":"en","created_at":"2022-03-16T21:43:37.000Z","author_id":"1259130000969588737","reply_settings":"everyone","conversation_id":"1504211813520400390","id":"1504211813520400390"},{"text":"Omicron linked to rise in croup in babies, TB vaccine improves immune response to virus - studies https://t.co/fwEKoL2oGI","possibly_sensitive":false,"source":"dlvr.it","lang":"en","created_at":"2022-03-16T21:43:37.000Z","author_id":"309325348","reply_settings":"everyone","conversation_id":"1504211810387329026","id":"1504211810387329026"},{"text":"COVID vaccine mandates, passes to become 'an employment issue' - lawyer https://t.co/rze7tuYwqw","possibly_sensitive":false,"source":"dlvr.it","lang":"en","created_at":"2022-03-16T21:43:33.000Z","author_id":"309325348","reply_settings":"everyone","conversation_id":"1504211796156039169","id":"1504211796156039169"},{"text":"ワイもワクチン打ってないから反ワクチン派ということになるんだが、反ワクチンの人はそう思ってるだけで問題ないけど、人様に迷惑かける反ワクチン過激派はやめてほしいし暴れることでコロナに感染するリスク上がるんじゃない？大丈夫？ https://t.co/KP0TSDYXbG","possibly_sensitive":false,"source":"Twitter for Android","lang":"ja","created_at":"2022-03-16T21:43:32.000Z","author_id":"1483270233758769153","reply_settings":"everyone","conversation_id":"1504211790883741701","id":"1504211790883741701"},{"in_reply_to_user_id":"1501341376796979202","text":"@BlowerRural @DonnaI16876888 @CDCgov All of them https://t.co/JLInT5WMo5","possibly_sensitive":false,"source":"Twitter for iPhone","lang":"en","created_at":"2022-03-16T21:43:31.000Z","author_id":"1347917501150224389","reply_settings":"everyone","conversation_id":"1503834671372595200","id":"1504211786098163720"},{"in_reply_to_user_id":"1433554491928834051","text":"@Girlonyourscre4 @McalexMcintyre @a_longhurst 2. No adverse effects in the report has been tied to vaccinations.\n\nThe leading, serious adverse effect, was definitely, NOT, vaccine related. It was, literally, COVID.\nhttps:/twitter.com/Truth_in_Number/status/1502413716008099841","possibly_sensitive":false,"source":"Twitter for Android","lang":"en","created_at":"2022-03-16T21:43:30.000Z","author_id":"1433554491928834051","reply_settings":"everyone","conversation_id":"1503935098680344582","id":"1504211781840879617"},{"in_reply_to_user_id":"41634520","text":"@seanhannity Covid,all shutdowns were following trump's task force recommendations.True,blue govs had the bells to follow them. R states became 20 of the worst 22 states with Covid death's AFTER THE VACCINE,worst 16 now.Nothing Joe can do about Rs killing their constituents to own a lib POTUS","possibly_sensitive":false,"source":"Twitter for Android","lang":"en","created_at":"2022-03-16T21:43:26.000Z","author_id":"1442574063315001347","reply_settings":"everyone","conversation_id":"1504207012598620160","id":"1504211765185421314"},{"in_reply_to_user_id":"22214972","text":"@WPBF25News nothing against you guys but I don’t know how you can report on another Pfizer vaccine without laughing.","possibly_sensitive":false,"source":"Twitter for iPhone","lang":"en","created_at":"2022-03-16T21:43:24.000Z","author_id":"1455337594708013066","reply_settings":"everyone","conversation_id":"1504211758239600647","id":"1504211758239600647"},{"in_reply_to_user_id":"1467228402","text":"@IndiGo6E please confirm Saudi quarantine policy. as per loca new policy no more quarantine required for Saudi Approved vaccine.Indian adults travelling to Riyadh on 2nd April. double vaccinated in India. do we need institutional quarantine? as per Indigo website its needed","possibly_sensitive":false,"source":"Twitter Web App","lang":"en","created_at":"2022-03-16T21:43:21.000Z","author_id":"101874931","reply_settings":"everyone","conversation_id":"1504211744457396224","id":"1504211744457396224"},{"in_reply_to_user_id":"1181892854769213440","text":"@sergiodde @GomezMicheline1 Poutine est lui même triplement vacciné, et a fortement encouragé à la vaccination","possibly_sensitive":false,"source":"Twitter for iPhone","lang":"fr","created_at":"2022-03-16T21:43:20.000Z","author_id":"507759587","reply_settings":"everyone","conversation_id":"1504029080420855813","id":"1504211740623613952"},{"in_reply_to_user_id":"96906231","text":"@thevivafrei For a young person the risk of the vaccine is the same as COVID","possibly_sensitive":false,"source":"Twitter for iPad","lang":"en","created_at":"2022-03-16T21:43:18.000Z","author_id":"1402579638","reply_settings":"everyone","conversation_id":"1504138637281267714","id":"1504211733967212545"},{"in_reply_to_user_id":"833565499032166400","text":"@Bridgetpee Sadly, having no regard for other people comes with the territory. You can’t be anti-vaccine unless this is your default position. I hope your husband is doing better and you have the support you need.","possibly_sensitive":false,"source":"Twitter for iPhone","lang":"en","created_at":"2022-03-16T21:43:17.000Z","author_id":"299580303","reply_settings":"everyone","conversation_id":"1503829702347476992","id":"1504211726191177728"},{"text":"Never forget how the FDA, Pfizer and other vaccine companies fooled us to make a sale. Experts don’t make mistakes like these. Intentionally not showing the relative risk reduction of less than 1% is a crime! #BigPharma #falseclaim #Pfizer https://t.co/usXGkOByBG","possibly_sensitive":false,"attachments":{"media_keys":["3_1504211713813807104"]},"source":"Twitter for iPhone","lang":"en","created_at":"2022-03-16T21:43:15.000Z","author_id":"37396896","reply_settings":"everyone","conversation_id":"1504211720155262976","id":"1504211720155262976"},{"text":"The world needs a recruitment surge in pathology. It’s convenient that hospitals/pathology is backlogged right now. Many entitled to vaccine injury compensation will not get it only those who pay private for private pathology will. ⁦@DowdEdward⁩ ⬇️ https://t.co/Gyr2CXpByh","possibly_sensitive":false,"source":"Twitter for iPad","lang":"en","created_at":"2022-03-16T21:43:14.000Z","author_id":"533420902","reply_settings":"everyone","conversation_id":"1504211714954436608","id":"1504211714954436608"},{"in_reply_to_user_id":"4163378603","text":"@c_tiot The vaccine does protect Pfizer from lawsuits","possibly_sensitive":false,"source":"Twitter for Android","lang":"en","created_at":"2022-03-16T21:43:05.000Z","author_id":"1281677060457418752","reply_settings":"everyone","conversation_id":"1504070624871804928","id":"1504211677424013312"},{"in_reply_to_user_id":"719192850848686080","text":"@Casperhafnia @RickJBrody @AlbaneseLaura @chayesmatthew NYC commercial cleaning, vaccinated or no job, no benefits, nothing even if you are not medically able.  Get the vaccine or lose your job.  Same with nurses, police, teachers, etc.","possibly_sensitive":false,"source":"Twitter for iPhone","lang":"en","created_at":"2022-03-16T21:43:04.000Z","author_id":"342664475","reply_settings":"everyone","conversation_id":"1504123967254241281","id":"1504211674055720960"},{"text":"https://t.co/Kg2jyrmKqf","possibly_sensitive":false,"source":"Twitter Web App","lang":"und","created_at":"2022-03-16T21:43:03.000Z","author_id":"81664859","reply_settings":"everyone","conversation_id":"1504211669618249739","id":"1504211669618249739"},{"text":"Bharat Biotech partners with Biofabri to develop TB vaccine - CanIndia News https://t.co/bG4qv6eUkm","possibly_sensitive":false,"source":"dlvr.it","lang":"en","created_at":"2022-03-16T21:43:03.000Z","author_id":"1232561474842718208","reply_settings":"everyone","conversation_id":"1504211667495768065","id":"1504211667495768065"},{"in_reply_to_user_id":"734703626099232768","text":"@AvonandsomerRob Natural immunity superior to vaccine\nhttps://t.co/GmUjuqRKnL","possibly_sensitive":false,"source":"Twitter Web App","lang":"en","created_at":"2022-03-16T21:43:00.000Z","author_id":"842117221497344001","reply_settings":"everyone","conversation_id":"1504017623561949185","id":"1504211655818981381"},{"text":"He was a teacher of, and collaborator with, Edward Jenner, pioneer of the smallpox vaccine.He is alleged to have paid for the stolen body of Charles Byrne, and proceeded to study and exhibit it against the deceased's explicit wishes.","possibly_sensitive":false,"source":"Twitter for Android","lang":"en","created_at":"2022-03-16T21:43:00.000Z","author_id":"1503871430303182851","reply_settings":"everyone","conversation_id":"1504211654711472128","id":"1504211654711472128"},{"in_reply_to_user_id":"20711586","text":"@GlobalBC https://t.co/qo1o8nYSx6\n\nWhy is it so important to \"boost numbers\" when children are not at risk from Covid? In fact, they are at far greater risk from the vaccine. Unless a child is in a special risk group due to some other condition, there is no reason to Covid-vaccinate them.","possibly_sensitive":false,"source":"Twitter Web App","lang":"en","created_at":"2022-03-16T21:42:56.000Z","author_id":"1217712231246454785","reply_settings":"everyone","conversation_id":"1503883750198763527","id":"1504211640438464520"},{"in_reply_to_user_id":"140519774","text":"@rosadelauro What protection? You were vaccinated and boosted and still got Covid-19?  So the vaccine doesn't work.  This is so comical that every time someone gets Covid they thank the faulty vaccine. Just amazing.","possibly_sensitive":false,"source":"Twitter Web App","lang":"en","created_at":"2022-03-16T21:42:49.000Z","author_id":"1038568848524361729","reply_settings":"everyone","conversation_id":"1502721527753715733","id":"1504211609283047424"},{"in_reply_to_user_id":"1483408249999159296","text":"@SeanBragg72 @phyxx Pretty ignorant comment. Read the report, it's world wide. There is more to the world than the USA. I was not mandaded to get any vaccine as of Feb 2021. There was no vaccine available either.","possibly_sensitive":false,"source":"Twitter Web App","lang":"en","created_at":"2022-03-16T21:42:45.000Z","author_id":"207132968","reply_settings":"everyone","conversation_id":"1503456972133191680","id":"1504211594695221251"},{"text":"Our work shared by Reuters! @Reuters @tbivala1 @BishaiLab @Yegnalab @HopkinsMedNews @HopkinsMedicine \n\nOmicron linked to rise in croup in babies; TB vaccine improves immune response to coronavirus https://t.co/sl1OGtMhM6","possibly_sensitive":false,"source":"Twitter for iPad","lang":"en","created_at":"2022-03-16T21:42:45.000Z","author_id":"285652025","reply_settings":"everyone","conversation_id":"1504211593114050570","id":"1504211593114050570"},{"in_reply_to_user_id":"1348681650","text":"@PeeVerbs @goodfoodgal If you want to look at outcome by vaccine status and age in one specific location you can - some countries publish that information and it confirms what this chart suggests in general - unvaccinated individuals have a much greater risk of death than vaccinated.","possibly_sensitive":false,"source":"Twitter for Android","lang":"en","created_at":"2022-03-16T21:42:44.000Z","author_id":"4914609770","reply_settings":"everyone","conversation_id":"1504047247645806592","id":"1504211590274764802"},{"text":"Ukraine just silently announced: First country to implement WEF's ‘Great Reset’ by setting up a Social Credit Application combining:\nUniversal Basic Income (UBI),\nDigital Identity &amp;\nVaccine Passport all within their Diia app\n\n@RepMTG @MeidasTouch @ColumbiaBugle https://t.co/s2vm7uptoU","possibly_sensitive":false,"source":"Twitter Web App","lang":"en","created_at":"2022-03-16T21:42:44.000Z","author_id":"1259130000969588737","reply_settings":"everyone","conversation_id":"1504211588219166725","id":"1504211588219166725"},{"in_reply_to_user_id":"1499959466430717952","text":"@dogspink3 @eric @StevenRad3 @PrimaryRinos22 @SheriMAGAA @AppSame @skb_sara @PatriotGaGa1 @JVER2ME @SusanGPatriot @UrgentNews911 @RicklesRevenge Suggestion for the Mayor...be a leader.. remove the vaccine mandate for sports and reinstate the 1400 city employees that lost their jobs due to the mandate","possibly_sensitive":false,"source":"Twitter for Android","lang":"en","created_at":"2022-03-16T21:42:43.000Z","author_id":"1353863406504337410","reply_settings":"everyone","conversation_id":"1501646894560329728","id":"1504211584134127617"},{"in_reply_to_user_id":"1926075181","text":"@OccupyMyGov Pfizer will create an ineffective vaccine and people will take it and claim it works because they haven’t died “yet”.","possibly_sensitive":false,"source":"Twitter for iPhone","lang":"en","created_at":"2022-03-16T21:42:41.000Z","author_id":"1369523532544180226","reply_settings":"everyone","conversation_id":"1503945722034413568","id":"1504211576760725504"},{"text":"If i aint the illest nigga im his new vaccine","possibly_sensitive":false,"source":"Twitter for iPhone","lang":"en","created_at":"2022-03-16T21:42:40.000Z","author_id":"405847374","reply_settings":"everyone","conversation_id":"1504211574042550278","id":"1504211574042550278"},{"text":"Florida health official put on 2-month leave after urging staff to get vaccine https://t.co/3O6THffm7H","possibly_sensitive":false,"source":"Twitter Web App","lang":"en","created_at":"2022-03-16T21:42:39.000Z","author_id":"1004907886575783936","reply_settings":"everyone","conversation_id":"1504211570456416257","id":"1504211570456416257"},{"text":"#AnthonyFauci\nFuck your vaccine AND EXPLAIN TO AMERICA WHY YOU LIED AND DONT TRY AND SPIN SHIT!!! THE FDA JUST SIGNED YOUR DEATH WARRANT,  YOU'RE GUILTY OF GENOCIDE,  SCUMBAG!!","possibly_sensitive":false,"source":"Twitter for Android","lang":"en","created_at":"2022-03-16T21:42:39.000Z","author_id":"1504004762248830977","reply_settings":"everyone","conversation_id":"1504211570041270276","id":"1504211570041270276"},{"in_reply_to_user_id":"26545630","text":"@heyjude14 @KR4HRC @JonChatman @ShellyDietzler @duelly87 Yes they did said. CDC WHO stated this.  As an ER nurse for 26 yrs. This was by far the biggest lie to the world. It's a virus just as bad as the flu.  And guess what they don't stop you from working if you don't get flu vaccine. That is just as contagious. Not checking for that","possibly_sensitive":false,"source":"Twitter for Android","lang":"en","created_at":"2022-03-16T21:42:39.000Z","author_id":"64398593","reply_settings":"everyone","conversation_id":"1503941343189430275","id":"1504211567398858757"},{"in_reply_to_user_id":"2417586104","text":"@SebGorka They should have gotten the vaccine and booster...never mind.","possibly_sensitive":false,"source":"Twitter for Android","lang":"en","created_at":"2022-03-16T21:42:37.000Z","author_id":"1417232433309798403","reply_settings":"everyone","conversation_id":"1504208385360613376","id":"1504211561820430342"},{"text":"I can’t believe this actually happened and it’s because he didn’t take the vaccine \n\nYou 1000% know it’s because of that https://t.co/NejmZK85Uj","possibly_sensitive":false,"source":"Twitter for iPhone","lang":"en","created_at":"2022-03-16T21:42:35.000Z","author_id":"3376471342","reply_settings":"everyone","conversation_id":"1504211550004985863","id":"1504211550004985863"},{"in_reply_to_user_id":"398785825","text":"@DIVIZIO1 J arrive toujours pas à comprendre comment des personnes comme maitre Divizio arrive à garder leurs calme face à tant de stupidité et bêtise. On suspend des non vacciné négatif au test mais on oblige de soignants positif covid a bosser car plus de personnelles c c est la réalité","possibly_sensitive":false,"source":"Twitter for Android","lang":"fr","created_at":"2022-03-16T21:42:31.000Z","author_id":"1477976522984235015","reply_settings":"everyone","conversation_id":"1504183630125580300","id":"1504211535094292484"},{"in_reply_to_user_id":"211658442","text":"@maskedannie5 @michaelpbreton 1 hour ago.\n\nUkraine just silently announced it’s the first country to implement the WEF's ‘Great Reset’ by setting up a Social Credit Application combining Universal Basic Income (UBI), a Digital Identity &amp; a Vaccine Passport all within their Diia app.","possibly_sensitive":false,"source":"Twitter Web App","lang":"en","created_at":"2022-03-16T21:42:30.000Z","author_id":"1563092491","reply_settings":"everyone","conversation_id":"1504200126872657928","id":"1504211530287620100"},{"in_reply_to_user_id":"73299652","text":"@TheoFleury14 Were there more people at the Ottawa convoy than those 'injured' by the vaccine?","possibly_sensitive":false,"source":"Twitter Web App","lang":"en","created_at":"2022-03-16T21:42:26.000Z","author_id":"264329377","reply_settings":"everyone","conversation_id":"1504208133568180226","id":"1504211511991959555"},{"text":"“Incidents of hypercoagulability after receiving different types of COVID-19 vaccine have been reported. The incidence of deep vein thrombosis (DVT) is about 1 in 1000, and about 50% of these patients with DVT develop pulmonary embolism (PE).” https://t.co/Wf7pifvVuY","possibly_sensitive":false,"source":"Twitter for iPhone","lang":"en","created_at":"2022-03-16T21:42:25.000Z","author_id":"801569962921955328","reply_settings":"everyone","conversation_id":"1504211510687674375","id":"1504211510687674375"}]